sysdynutils/__init__.py
sysdynutils/statespacesymbolic.py
sysdynutils/sysdyn.py
sysdynutils-0.1.0.dist-info/LICENSE
sysdynutils-0.1.0.dist-info/METADATA
sysdynutils-0.1.0.dist-info/WHEEL
sysdynutils-0.1.0.dist-info/RECORD
